fiptool/__init__.py
fiptool/core.py
tests/__init__.py
tests/test_fiptool.py
fiptool-0.1.2.dist-info/LICENSE
fiptool-0.1.2.dist-info/METADATA
fiptool-0.1.2.dist-info/WHEEL
fiptool-0.1.2.dist-info/entry_points.txt
fiptool-0.1.2.dist-info/top_level.txt
fiptool-0.1.2.dist-info/RECORD
